kkdcpasn1
