Metadata-Version: 1.1
Name: kkdcpasn1
Version: 0.2
Summary: High performance ASN.1 parser for Kerberos KDC Proxy [KKDCP]
Home-page: https://github.com/tiran/kkdcpasn1
Author: Latchset Contributors
Author-email: cheimes@redhat.com
License: MIT
Keywords: asn1 kkdcp kerberos proxy
Platform: UNKNOWN
Classifier: Development Status :: 4 - Beta
Classifier: Programming Language :: Cython
Classifier: Programming Language :: C
Classifier: Programming Language :: Python :: 2.7
Classifier: Programming Language :: Python :: 3.4
Classifier: Programming Language :: Python :: 3.5
Classifier: Programming Language :: Python :: 3.6
Classifier: Intended Audience :: Developers
Classifier: Topic :: Security
Classifier: Topic :: Software Development :: Libraries :: Python Modules
